<?xml version="1.0" encoding='UTF-8'?>
<matrices>
  <matriz m="15" n="15" nombre="Avanzado_m1">
    <dato x="1" y="1">0</dato>
    <dato x="1" y="2">103</dato>
    <dato x="1" y="3">0</dato>
    <dato x="1" y="4">105</dato>
    <dato x="1" y="5">0</dato>
    <dato x="1" y="6">0</dato>
    <dato x="1" y="7">201</dato>
    <dato x="1" y="8">301</dato>
    <dato x="1" y="9">0</dato>
    <dato x="1" y="10">0</dato>
    <dato x="1" y="11">404</dato>
    <dato x="1" y="12">501</dato>
    <dato x="1" y="13">0</dato>
    <dato x="1" y="14">605</dato>
    <dato x="1" y="15">0</dato>
    <dato x="2" y="1">31</dato>
    <dato x="2" y="2">51</dato>
    <dato x="2" y="3">77</dato>
    <dato x="2" y="4">90</dato>
    <dato x="2" y="5">91</dato>
    <dato x="2" y="6">101</dato>
    <dato x="2" y="7">102</dato>
    <dato x="2" y="8">102</dato>
    <dato x="2" y="9">103</dato>
    <dato x="2" y="10">103</dato>
    <dato x="2" y="11">102</dato>
    <dato x="2" y="12">102</dato>
    <dato x="2" y="13">103</dato>
    <dato x="2" y="14">106</dato>
    <dato x="2" y="15">110</dato>
    <dato x="3" y="1">0</dato>
    <dato x="3" y="2">1002</dato>
    <dato x="3" y="3">2004</dato>
    <dato x="3" y="4">5005</dato>
    <dato x="3" y="5">0</dato>
    <dato x="3" y="6">701</dato>
    <dato x="3" y="7">90</dato>
    <dato x="3" y="8">42</dato>
    <dato x="3" y="9">0</dato>
    <dato x="3" y="10">3</dato>
    <dato x="3" y="11">2</dato>
    <dato x="3" y="12">2</dato>
    <dato x="3" y="13">3</dato>
    <dato x="3" y="14">6</dato>
    <dato x="3" y="15">0</dato>
    <dato x="4" y="1">11</dato>
    <dato x="4" y="2">10</dato>
    <dato x="4" y="3">94</dato>
    <dato x="4" y="4">85</dato>
    <dato x="4" y="5">66</dato>
    <dato x="4" y="6">27</dato>
    <dato x="4" y="7">41</dato>
    <dato x="4" y="8">12</dato>
    <dato x="4" y="9">57</dato>
    <dato x="4" y="10">43</dato>
    <dato x="4" y="11">92</dato>
    <dato x="4" y="12">52</dato>
    <dato x="4" y="13">13</dato>
    <dato x="4" y="14">16</dato>
    <dato x="4" y="15">770</dato>
    <dato x="5" y="1">0</dato>
    <dato x="5" y="2">1001</dato>
    <dato x="5" y="3">2005</dato>
    <dato x="5" y="4">5007</dato>
    <dato x="5" y="5">0</dato>
    <dato x="5" y="6">703</dato>
    <dato x="5" y="7">91</dato>
    <dato x="5" y="8">52</dato>
    <dato x="5" y="9">0</dato>
    <dato x="5" y="10">3</dato>
    <dato x="5" y="11">2</dato>
    <dato x="5" y="12">2</dato>
    <dato x="5" y="13">3</dato>
    <dato x="5" y="14">6</dato>
    <dato x="5" y="15">0</dato>
    <dato x="6" y="1">13</dato>
    <dato x="6" y="2">93</dato>
    <dato x="6" y="3">54</dato>
    <dato x="6" y="4">65</dato>
    <dato x="6" y="5">26</dato>
    <dato x="6" y="6">0</dato>
    <dato x="6" y="7">0</dato>
    <dato x="6" y="8">0</dato>
    <dato x="6" y="9">38</dato>
    <dato x="6" y="10">57</dato>
    <dato x="6" y="11">54</dato>
    <dato x="6" y="12">74</dato>
    <dato x="6" y="13">39</dato>
    <dato x="6" y="14">23</dato>
    <dato x="6" y="15">0</dato>
    <dato x="7" y="1">13</dato>
    <dato x="7" y="2">10</dato>
    <dato x="7" y="3">94</dato>
    <dato x="7" y="4">85</dato>
    <dato x="7" y="5">66</dato>
    <dato x="7" y="6">27</dato>
    <dato x="7" y="7">41</dato>
    <dato x="7" y="8">12</dato>
    <dato x="7" y="9">58</dato>
    <dato x="7" y="10">43</dato>
    <dato x="7" y="11">92</dato>
    <dato x="7" y="12">52</dato>
    <dato x="7" y="13">13</dato>
    <dato x="7" y="14">16</dato>
    <dato x="7" y="15">770</dato>
    <dato x="8" y="1">0</dato>
    <dato x="8" y="2">101</dato>
    <dato x="8" y="3">0</dato>
    <dato x="8" y="4">107</dato>
    <dato x="8" y="5">0</dato>
    <dato x="8" y="6">0</dato>
    <dato x="8" y="7">203</dato>
    <dato x="8" y="8">302</dato>
    <dato x="8" y="9">0</dato>
    <dato x="8" y="10">0</dato>
    <dato x="8" y="11">402</dato>
    <dato x="8" y="12">505</dato>
    <dato x="8" y="13">0</dato>
    <dato x="8" y="14">607</dato>
    <dato x="8" y="15">0</dato>
    <dato x="9" y="1">16</dato>
    <dato x="9" y="2">13</dato>
    <dato x="9" y="3">94</dato>
    <dato x="9" y="4">85</dato>
    <dato x="9" y="5">66</dato>
    <dato x="9" y="6">27</dato>
    <dato x="9" y="7">41</dato>
    <dato x="9" y="8">12</dato>
    <dato x="9" y="9">50</dato>
    <dato x="9" y="10">43</dato>
    <dato x="9" y="11">92</dato>
    <dato x="9" y="12">52</dato>
    <dato x="9" y="13">13</dato>
    <dato x="9" y="14">16</dato>
    <dato x="9" y="15">770</dato>
    <dato x="10" y="1">0</dato>
    <dato x="10" y="2">1003</dato>
    <dato x="10" y="3">2006</dato>
    <dato x="10" y="4">5010</dato>
    <dato x="10" y="5">0</dato>
    <dato x="10" y="6">931</dato>
    <dato x="10" y="7">92</dato>
    <dato x="10" y="8">62</dato>
    <dato x="10" y="9">0</dato>
    <dato x="10" y="10">3</dato>
    <dato x="10" y="11">2</dato>
    <dato x="10" y="12">2</dato>
    <dato x="10" y="13">3</dato>
    <dato x="10" y="14">6</dato>
    <dato x="10" y="15">0</dato>
    <dato x="11" y="1">14</dato>
    <dato x="11" y="2">13</dato>
    <dato x="11" y="3">94</dato>
    <dato x="11" y="4">85</dato>
    <dato x="11" y="5">66</dato>
    <dato x="11" y="6">27</dato>
    <dato x="11" y="7">41</dato>
    <dato x="11" y="8">12</dato>
    <dato x="11" y="9">51</dato>
    <dato x="11" y="10">43</dato>
    <dato x="11" y="11">92</dato>
    <dato x="11" y="12">52</dato>
    <dato x="11" y="13">13</dato>
    <dato x="11" y="14">16</dato>
    <dato x="11" y="15">770</dato>
    <dato x="12" y="1">11</dato>
    <dato x="12" y="2">38</dato>
    <dato x="12" y="3">47</dato>
    <dato x="12" y="4">35</dato>
    <dato x="12" y="5">56</dato>
    <dato x="12" y="6">0</dato>
    <dato x="12" y="7">0</dato>
    <dato x="12" y="8">0</dato>
    <dato x="12" y="9">89</dato>
    <dato x="12" y="10">21</dato>
    <dato x="12" y="11">32</dato>
    <dato x="12" y="12">12</dato>
    <dato x="12" y="13">21</dato>
    <dato x="12" y="14">42</dato>
    <dato x="12" y="15">0</dato>
    <dato x="13" y="1">12</dato>
    <dato x="13" y="2">10</dato>
    <dato x="13" y="3">94</dato>
    <dato x="13" y="4">85</dato>
    <dato x="13" y="5">66</dato>
    <dato x="13" y="6">27</dato>
    <dato x="13" y="7">41</dato>
    <dato x="13" y="8">12</dato>
    <dato x="13" y="9">52</dato>
    <dato x="13" y="10">43</dato>
    <dato x="13" y="11">92</dato>
    <dato x="13" y="12">52</dato>
    <dato x="13" y="13">13</dato>
    <dato x="13" y="14">16</dato>
    <dato x="13" y="15">770</dato>
    <dato x="14" y="1">0</dato>
    <dato x="14" y="2">100</dato>
    <dato x="14" y="3">0</dato>
    <dato x="14" y="4">110</dato>
    <dato x="14" y="5">0</dato>
    <dato x="14" y="6">0</dato>
    <dato x="14" y="7">204</dato>
    <dato x="14" y="8">303</dato>
    <dato x="14" y="9">0</dato>
    <dato x="14" y="10">0</dato>
    <dato x="14" y="11">401</dato>
    <dato x="14" y="12">506</dato>
    <dato x="14" y="13">0</dato>
    <dato x="14" y="14">608</dato>
    <dato x="14" y="15">0</dato>
    <dato x="15" y="1">12</dato>
    <dato x="15" y="2">34</dato>
    <dato x="15" y="3">74</dato>
    <dato x="15" y="4">51</dato>
    <dato x="15" y="5">96</dato>
    <dato x="15" y="6">0</dato>
    <dato x="15" y="7">0</dato>
    <dato x="15" y="8">0</dato>
    <dato x="15" y="9">99</dato>
    <dato x="15" y="10">42</dato>
    <dato x="15" y="11">12</dato>
    <dato x="15" y="12">11</dato>
    <dato x="15" y="13">82</dato>
    <dato x="15" y="14">14</dato>
    <dato x="15" y="15">0</dato>
  </matriz>
  <matriz m="15" n="15" nombre="Avanzado_m2">
    <dato x="1" y="1">0</dato>
    <dato x="1" y="2">103</dato>
    <dato x="1" y="3">0</dato>
    <dato x="1" y="4">105</dato>
    <dato x="1" y="5">0</dato>
    <dato x="1" y="6">0</dato>
    <dato x="1" y="7">201</dato>
    <dato x="1" y="8">301</dato>
    <dato x="1" y="9">0</dato>
    <dato x="1" y="10">0</dato>
    <dato x="1" y="11">404</dato>
    <dato x="1" y="12">501</dato>
    <dato x="1" y="13">0</dato>
    <dato x="1" y="14">605</dato>
    <dato x="1" y="15">0</dato>
    <dato x="2" y="1">0</dato>
    <dato x="2" y="2">51</dato>
    <dato x="2" y="3">77</dato>
    <dato x="2" y="4">90</dato>
    <dato x="2" y="5">91</dato>
    <dato x="2" y="6">0</dato>
    <dato x="2" y="7">102</dato>
    <dato x="2" y="8">102</dato>
    <dato x="2" y="9">103</dato>
    <dato x="2" y="10">103</dato>
    <dato x="2" y="11">102</dato>
    <dato x="2" y="12">102</dato>
    <dato x="2" y="13">103</dato>
    <dato x="2" y="14">106</dato>
    <dato x="2" y="15">0</dato>
    <dato x="3" y="1">0</dato>
    <dato x="3" y="2">1002</dato>
    <dato x="3" y="3">2004</dato>
    <dato x="3" y="4">5005</dato>
    <dato x="3" y="5">0</dato>
    <dato x="3" y="6">701</dato>
    <dato x="3" y="7">90</dato>
    <dato x="3" y="8">42</dato>
    <dato x="3" y="9">0</dato>
    <dato x="3" y="10">3</dato>
    <dato x="3" y="11">2</dato>
    <dato x="3" y="12">2</dato>
    <dato x="3" y="13">3</dato>
    <dato x="3" y="14">6</dato>
    <dato x="3" y="15">0</dato>
    <dato x="4" y="1">11</dato>
    <dato x="4" y="2">10</dato>
    <dato x="4" y="3">94</dato>
    <dato x="4" y="4">85</dato>
    <dato x="4" y="5">66</dato>
    <dato x="4" y="6">27</dato>
    <dato x="4" y="7">41</dato>
    <dato x="4" y="8">12</dato>
    <dato x="4" y="9">57</dato>
    <dato x="4" y="10">43</dato>
    <dato x="4" y="11">92</dato>
    <dato x="4" y="12">52</dato>
    <dato x="4" y="13">13</dato>
    <dato x="4" y="14">16</dato>
    <dato x="4" y="15">770</dato>
    <dato x="5" y="1">0</dato>
    <dato x="5" y="2">1001</dato>
    <dato x="5" y="3">2005</dato>
    <dato x="5" y="4">5007</dato>
    <dato x="5" y="5">0</dato>
    <dato x="5" y="6">703</dato>
    <dato x="5" y="7">91</dato>
    <dato x="5" y="8">52</dato>
    <dato x="5" y="9">0</dato>
    <dato x="5" y="10">3</dato>
    <dato x="5" y="11">2</dato>
    <dato x="5" y="12">2</dato>
    <dato x="5" y="13">3</dato>
    <dato x="5" y="14">6</dato>
    <dato x="5" y="15">0</dato>
    <dato x="6" y="1">13</dato>
    <dato x="6" y="2">93</dato>
    <dato x="6" y="3">54</dato>
    <dato x="6" y="4">65</dato>
    <dato x="6" y="5">26</dato>
    <dato x="6" y="6">0</dato>
    <dato x="6" y="7">0</dato>
    <dato x="6" y="8">0</dato>
    <dato x="6" y="9">38</dato>
    <dato x="6" y="10">57</dato>
    <dato x="6" y="11">54</dato>
    <dato x="6" y="12">74</dato>
    <dato x="6" y="13">39</dato>
    <dato x="6" y="14">23</dato>
    <dato x="6" y="15">0</dato>
    <dato x="7" y="1">13</dato>
    <dato x="7" y="2">10</dato>
    <dato x="7" y="3">94</dato>
    <dato x="7" y="4">85</dato>
    <dato x="7" y="5">66</dato>
    <dato x="7" y="6">27</dato>
    <dato x="7" y="7">41</dato>
    <dato x="7" y="8">12</dato>
    <dato x="7" y="9">58</dato>
    <dato x="7" y="10">43</dato>
    <dato x="7" y="11">92</dato>
    <dato x="7" y="12">52</dato>
    <dato x="7" y="13">13</dato>
    <dato x="7" y="14">16</dato>
    <dato x="7" y="15">770</dato>
    <dato x="8" y="1">0</dato>
    <dato x="8" y="2">101</dato>
    <dato x="8" y="3">0</dato>
    <dato x="8" y="4">107</dato>
    <dato x="8" y="5">0</dato>
    <dato x="8" y="6">0</dato>
    <dato x="8" y="7">203</dato>
    <dato x="8" y="8">302</dato>
    <dato x="8" y="9">0</dato>
    <dato x="8" y="10">0</dato>
    <dato x="8" y="11">402</dato>
    <dato x="8" y="12">505</dato>
    <dato x="8" y="13">0</dato>
    <dato x="8" y="14">607</dato>
    <dato x="8" y="15">0</dato>
    <dato x="9" y="1">0</dato>
    <dato x="9" y="2">13</dato>
    <dato x="9" y="3">94</dato>
    <dato x="9" y="4">85</dato>
    <dato x="9" y="5">66</dato>
    <dato x="9" y="6">0</dato>
    <dato x="9" y="7">41</dato>
    <dato x="9" y="8">12</dato>
    <dato x="9" y="9">50</dato>
    <dato x="9" y="10">43</dato>
    <dato x="9" y="11">92</dato>
    <dato x="9" y="12">52</dato>
    <dato x="9" y="13">13</dato>
    <dato x="9" y="14">16</dato>
    <dato x="9" y="15">0</dato>
    <dato x="10" y="1">0</dato>
    <dato x="10" y="2">1003</dato>
    <dato x="10" y="3">2006</dato>
    <dato x="10" y="4">5010</dato>
    <dato x="10" y="5">0</dato>
    <dato x="10" y="6">931</dato>
    <dato x="10" y="7">92</dato>
    <dato x="10" y="8">62</dato>
    <dato x="10" y="9">0</dato>
    <dato x="10" y="10">3</dato>
    <dato x="10" y="11">2</dato>
    <dato x="10" y="12">2</dato>
    <dato x="10" y="13">3</dato>
    <dato x="10" y="14">6</dato>
    <dato x="10" y="15">0</dato>
    <dato x="11" y="1">14</dato>
    <dato x="11" y="2">0</dato>
    <dato x="11" y="3">94</dato>
    <dato x="11" y="4">85</dato>
    <dato x="11" y="5">66</dato>
    <dato x="11" y="6">27</dato>
    <dato x="11" y="7">0</dato>
    <dato x="11" y="8">12</dato>
    <dato x="11" y="9">51</dato>
    <dato x="11" y="10">43</dato>
    <dato x="11" y="11">92</dato>
    <dato x="11" y="12">0</dato>
    <dato x="11" y="13">13</dato>
    <dato x="11" y="14">16</dato>
    <dato x="11" y="15">0</dato>
    <dato x="12" y="1">11</dato>
    <dato x="12" y="2">38</dato>
    <dato x="12" y="3">47</dato>
    <dato x="12" y="4">35</dato>
    <dato x="12" y="5">56</dato>
    <dato x="12" y="6">0</dato>
    <dato x="12" y="7">0</dato>
    <dato x="12" y="8">0</dato>
    <dato x="12" y="9">89</dato>
    <dato x="12" y="10">21</dato>
    <dato x="12" y="11">32</dato>
    <dato x="12" y="12">12</dato>
    <dato x="12" y="13">21</dato>
    <dato x="12" y="14">42</dato>
    <dato x="12" y="15">0</dato>
    <dato x="13" y="1">12</dato>
    <dato x="13" y="2">0</dato>
    <dato x="13" y="3">94</dato>
    <dato x="13" y="4">85</dato>
    <dato x="13" y="5">66</dato>
    <dato x="13" y="6">27</dato>
    <dato x="13" y="7">0</dato>
    <dato x="13" y="8">12</dato>
    <dato x="13" y="9">52</dato>
    <dato x="13" y="10">43</dato>
    <dato x="13" y="11">92</dato>
    <dato x="13" y="12">0</dato>
    <dato x="13" y="13">13</dato>
    <dato x="13" y="14">16</dato>
    <dato x="13" y="15">0</dato>
    <dato x="14" y="1">0</dato>
    <dato x="14" y="2">100</dato>
    <dato x="14" y="3">0</dato>
    <dato x="14" y="4">110</dato>
    <dato x="14" y="5">0</dato>
    <dato x="14" y="6">0</dato>
    <dato x="14" y="7">204</dato>
    <dato x="14" y="8">303</dato>
    <dato x="14" y="9">0</dato>
    <dato x="14" y="10">0</dato>
    <dato x="14" y="11">401</dato>
    <dato x="14" y="12">506</dato>
    <dato x="14" y="13">0</dato>
    <dato x="14" y="14">608</dato>
    <dato x="14" y="15">0</dato>
    <dato x="15" y="1">12</dato>
    <dato x="15" y="2">34</dato>
    <dato x="15" y="3">74</dato>
    <dato x="15" y="4">51</dato>
    <dato x="15" y="5">96</dato>
    <dato x="15" y="6">0</dato>
    <dato x="15" y="7">0</dato>
    <dato x="15" y="8">0</dato>
    <dato x="15" y="9">99</dato>
    <dato x="15" y="10">42</dato>
    <dato x="15" y="11">12</dato>
    <dato x="15" y="12">11</dato>
    <dato x="15" y="13">82</dato>
    <dato x="15" y="14">14</dato>
    <dato x="15" y="15">0</dato>
  </matriz>
  <matriz m="15" n="15" nombre="Avanzado_m3">
    <dato x="1" y="1">0</dato>
    <dato x="1" y="2">103</dato>
    <dato x="1" y="3">0</dato>
    <dato x="1" y="4">105</dato>
    <dato x="1" y="5">0</dato>
    <dato x="1" y="6">0</dato>
    <dato x="1" y="7">201</dato>
    <dato x="1" y="8">301</dato>
    <dato x="1" y="9">0</dato>
    <dato x="1" y="10">0</dato>
    <dato x="1" y="11">404</dato>
    <dato x="1" y="12">501</dato>
    <dato x="1" y="13">0</dato>
    <dato x="1" y="14">605</dato>
    <dato x="1" y="15">0</dato>
    <dato x="2" y="1">31</dato>
    <dato x="2" y="2">51</dato>
    <dato x="2" y="3">0</dato>
    <dato x="2" y="4">90</dato>
    <dato x="2" y="5">91</dato>
    <dato x="2" y="6">0</dato>
    <dato x="2" y="7">102</dato>
    <dato x="2" y="8">102</dato>
    <dato x="2" y="9">0</dato>
    <dato x="2" y="10">103</dato>
    <dato x="2" y="11">102</dato>
    <dato x="2" y="12">0</dato>
    <dato x="2" y="13">103</dato>
    <dato x="2" y="14">0</dato>
    <dato x="2" y="15">110</dato>
    <dato x="3" y="1">0</dato>
    <dato x="3" y="2">1002</dato>
    <dato x="3" y="3">2004</dato>
    <dato x="3" y="4">5005</dato>
    <dato x="3" y="5">0</dato>
    <dato x="3" y="6">701</dato>
    <dato x="3" y="7">90</dato>
    <dato x="3" y="8">42</dato>
    <dato x="3" y="9">0</dato>
    <dato x="3" y="10">3</dato>
    <dato x="3" y="11">2</dato>
    <dato x="3" y="12">2</dato>
    <dato x="3" y="13">3</dato>
    <dato x="3" y="14">6</dato>
    <dato x="3" y="15">0</dato>
    <dato x="4" y="1">0</dato>
    <dato x="4" y="2">10</dato>
    <dato x="4" y="3">94</dato>
    <dato x="4" y="4">85</dato>
    <dato x="4" y="5">0</dato>
    <dato x="4" y="6">27</dato>
    <dato x="4" y="7">41</dato>
    <dato x="4" y="8">12</dato>
    <dato x="4" y="9">0</dato>
    <dato x="4" y="10">43</dato>
    <dato x="4" y="11">92</dato>
    <dato x="4" y="12">52</dato>
    <dato x="4" y="13">13</dato>
    <dato x="4" y="14">16</dato>
    <dato x="4" y="15">0</dato>
    <dato x="5" y="1">0</dato>
    <dato x="5" y="2">1001</dato>
    <dato x="5" y="3">2005</dato>
    <dato x="5" y="4">5007</dato>
    <dato x="5" y="5">0</dato>
    <dato x="5" y="6">703</dato>
    <dato x="5" y="7">91</dato>
    <dato x="5" y="8">52</dato>
    <dato x="5" y="9">0</dato>
    <dato x="5" y="10">3</dato>
    <dato x="5" y="11">2</dato>
    <dato x="5" y="12">2</dato>
    <dato x="5" y="13">3</dato>
    <dato x="5" y="14">6</dato>
    <dato x="5" y="15">0</dato>
    <dato x="6" y="1">13</dato>
    <dato x="6" y="2">93</dato>
    <dato x="6" y="3">54</dato>
    <dato x="6" y="4">65</dato>
    <dato x="6" y="5">26</dato>
    <dato x="6" y="6">0</dato>
    <dato x="6" y="7">0</dato>
    <dato x="6" y="8">0</dato>
    <dato x="6" y="9">38</dato>
    <dato x="6" y="10">57</dato>
    <dato x="6" y="11">54</dato>
    <dato x="6" y="12">74</dato>
    <dato x="6" y="13">39</dato>
    <dato x="6" y="14">23</dato>
    <dato x="6" y="15">0</dato>
    <dato x="7" y="1">0</dato>
    <dato x="7" y="2">10</dato>
    <dato x="7" y="3">94</dato>
    <dato x="7" y="4">85</dato>
    <dato x="7" y="5">0</dato>
    <dato x="7" y="6">27</dato>
    <dato x="7" y="7">41</dato>
    <dato x="7" y="8">12</dato>
    <dato x="7" y="9">0</dato>
    <dato x="7" y="10">43</dato>
    <dato x="7" y="11">92</dato>
    <dato x="7" y="12">52</dato>
    <dato x="7" y="13">13</dato>
    <dato x="7" y="14">16</dato>
    <dato x="7" y="15">0</dato>
    <dato x="8" y="1">0</dato>
    <dato x="8" y="2">101</dato>
    <dato x="8" y="3">0</dato>
    <dato x="8" y="4">107</dato>
    <dato x="8" y="5">0</dato>
    <dato x="8" y="6">0</dato>
    <dato x="8" y="7">203</dato>
    <dato x="8" y="8">302</dato>
    <dato x="8" y="9">0</dato>
    <dato x="8" y="10">0</dato>
    <dato x="8" y="11">402</dato>
    <dato x="8" y="12">505</dato>
    <dato x="8" y="13">0</dato>
    <dato x="8" y="14">607</dato>
    <dato x="8" y="15">0</dato>
    <dato x="9" y="1">0</dato>
    <dato x="9" y="2">13</dato>
    <dato x="9" y="3">94</dato>
    <dato x="9" y="4">85</dato>
    <dato x="9" y="5">0</dato>
    <dato x="9" y="6">27</dato>
    <dato x="9" y="7">41</dato>
    <dato x="9" y="8">12</dato>
    <dato x="9" y="9">0</dato>
    <dato x="9" y="10">43</dato>
    <dato x="9" y="11">92</dato>
    <dato x="9" y="12">52</dato>
    <dato x="9" y="13">13</dato>
    <dato x="9" y="14">16</dato>
    <dato x="9" y="15">0</dato>
    <dato x="10" y="1">0</dato>
    <dato x="10" y="2">1003</dato>
    <dato x="10" y="3">2006</dato>
    <dato x="10" y="4">5010</dato>
    <dato x="10" y="5">0</dato>
    <dato x="10" y="6">931</dato>
    <dato x="10" y="7">92</dato>
    <dato x="10" y="8">62</dato>
    <dato x="10" y="9">0</dato>
    <dato x="10" y="10">3</dato>
    <dato x="10" y="11">2</dato>
    <dato x="10" y="12">2</dato>
    <dato x="10" y="13">3</dato>
    <dato x="10" y="14">6</dato>
    <dato x="10" y="15">0</dato>
    <dato x="11" y="1">14</dato>
    <dato x="11" y="2">13</dato>
    <dato x="11" y="3">0</dato>
    <dato x="11" y="4">85</dato>
    <dato x="11" y="5">66</dato>
    <dato x="11" y="6">0</dato>
    <dato x="11" y="7">41</dato>
    <dato x="11" y="8">12</dato>
    <dato x="11" y="9">0</dato>
    <dato x="11" y="10">43</dato>
    <dato x="11" y="11">92</dato>
    <dato x="11" y="12">0</dato>
    <dato x="11" y="13">13</dato>
    <dato x="11" y="14">0</dato>
    <dato x="11" y="15">770</dato>
    <dato x="12" y="1">11</dato>
    <dato x="12" y="2">38</dato>
    <dato x="12" y="3">47</dato>
    <dato x="12" y="4">35</dato>
    <dato x="12" y="5">56</dato>
    <dato x="12" y="6">0</dato>
    <dato x="12" y="7">0</dato>
    <dato x="12" y="8">0</dato>
    <dato x="12" y="9">89</dato>
    <dato x="12" y="10">21</dato>
    <dato x="12" y="11">32</dato>
    <dato x="12" y="12">12</dato>
    <dato x="12" y="13">21</dato>
    <dato x="12" y="14">42</dato>
    <dato x="12" y="15">0</dato>
    <dato x="13" y="1">12</dato>
    <dato x="13" y="2">10</dato>
    <dato x="13" y="3">0</dato>
    <dato x="13" y="4">85</dato>
    <dato x="13" y="5">66</dato>
    <dato x="13" y="6">0</dato>
    <dato x="13" y="7">41</dato>
    <dato x="13" y="8">12</dato>
    <dato x="13" y="9">0</dato>
    <dato x="13" y="10">43</dato>
    <dato x="13" y="11">92</dato>
    <dato x="13" y="12">0</dato>
    <dato x="13" y="13">13</dato>
    <dato x="13" y="14">0</dato>
    <dato x="13" y="15">770</dato>
    <dato x="14" y="1">0</dato>
    <dato x="14" y="2">100</dato>
    <dato x="14" y="3">0</dato>
    <dato x="14" y="4">110</dato>
    <dato x="14" y="5">0</dato>
    <dato x="14" y="6">0</dato>
    <dato x="14" y="7">204</dato>
    <dato x="14" y="8">303</dato>
    <dato x="14" y="9">0</dato>
    <dato x="14" y="10">0</dato>
    <dato x="14" y="11">401</dato>
    <dato x="14" y="12">506</dato>
    <dato x="14" y="13">0</dato>
    <dato x="14" y="14">608</dato>
    <dato x="14" y="15">0</dato>
    <dato x="15" y="1">12</dato>
    <dato x="15" y="2">34</dato>
    <dato x="15" y="3">74</dato>
    <dato x="15" y="4">51</dato>
    <dato x="15" y="5">96</dato>
    <dato x="15" y="6">0</dato>
    <dato x="15" y="7">0</dato>
    <dato x="15" y="8">0</dato>
    <dato x="15" y="9">99</dato>
    <dato x="15" y="10">42</dato>
    <dato x="15" y="11">12</dato>
    <dato x="15" y="12">11</dato>
    <dato x="15" y="13">82</dato>
    <dato x="15" y="14">14</dato>
    <dato x="15" y="15">0</dato>
  </matriz>
</matrices>
